aea_ledger_fetchai/__init__.py
aea_ledger_fetchai/_cosmos.py
aea_ledger_fetchai/fetchai.py
aea_ledger_fetchai-1.2.5.dist-info/LICENSE
aea_ledger_fetchai-1.2.5.dist-info/METADATA
aea_ledger_fetchai-1.2.5.dist-info/WHEEL
aea_ledger_fetchai-1.2.5.dist-info/entry_points.txt
aea_ledger_fetchai-1.2.5.dist-info/top_level.txt
aea_ledger_fetchai-1.2.5.dist-info/RECORD
