Metadata-Version: 2.1
Name: aea-ledger-fetchai
Version: 1.2.5
Summary: Python package wrapping the public and private key cryptography and ledger API of Fetch.AI.
Author: Fetch.AI Limited
License: Apache-2.0
Classifier: Environment :: Console
Classifier: Environment :: Web Environment
Classifier: Development Status :: 5 - Production/Stable
Classifier: Intended Audience :: Developers
Classifier: License :: OSI Approved :: Apache Software License
Classifier: Natural Language :: English
Classifier: Operating System :: MacOS
Classifier: Operating System :: Microsoft
Classifier: Operating System :: Unix
Classifier: Programming Language :: Python :: 3.6
Classifier: Programming Language :: Python :: 3.7
Classifier: Programming Language :: Python :: 3.8
Classifier: Programming Language :: Python :: 3.9
Classifier: Topic :: Communications
Classifier: Topic :: Internet
Classifier: Topic :: Software Development
License-File: LICENSE
Requires-Dist: aea (<2.0.0,>=1.0.0)
Requires-Dist: ecdsa (<0.17.0,>=0.15)
Requires-Dist: bech32 (==1.2.0)
Requires-Dist: pycryptodome (<4.0.0,>=3.10.1)
Requires-Dist: cosmpy (<0.7.0,>=0.6.2)
